jetflow/__init__.py
jetflow/__version__.py
jetflow/_action_wrappers.py
jetflow/action.py
jetflow/chain.py
jetflow/extract.py
jetflow/py.typed
jetflow/actions/__init__.py
jetflow/actions/chart_processing.py
jetflow/actions/chart_utils.py
jetflow/actions/plan.py
jetflow/actions/utils.py
jetflow/actions/web_search.py
jetflow/actions/e2b_python_exec/__init__.py
jetflow/actions/e2b_python_exec/action.py
jetflow/actions/e2b_python_exec/chart_extractor.py
jetflow/actions/e2b_python_exec/extract_widget.py
jetflow/actions/e2b_python_exec/sandbox.py
jetflow/actions/e2b_python_exec/storage.py
jetflow/actions/e2b_python_exec/tracking_code.py
jetflow/actions/e2b_python_exec/utils.py
jetflow/actions/e2b_python_exec_with_steps/__init__.py
jetflow/actions/e2b_python_exec_with_steps/action.py
jetflow/actions/exa_web_search/__init__.py
jetflow/actions/exa_web_search/action.py
jetflow/actions/local_python_exec/__init__.py
jetflow/actions/local_python_exec/action.py
jetflow/actions/local_python_exec/chart_extractor.py
jetflow/actions/local_python_exec/sandbox.py
jetflow/actions/local_python_exec/utils.py
jetflow/actions/serper_web_search/__init__.py
jetflow/actions/serper_web_search/action.py
jetflow/agent/__init__.py
jetflow/agent/async_.py
jetflow/agent/context.py
jetflow/agent/state.py
jetflow/agent/sync.py
jetflow/agent/utils.py
jetflow/cache/__init__.py
jetflow/cache/backend.py
jetflow/cache/client.py
jetflow/cache/events.py
jetflow/cache/key.py
jetflow/citations/__init__.py
jetflow/citations/async_middleware.py
jetflow/citations/extractor.py
jetflow/citations/state.py
jetflow/citations/sync_middleware.py
jetflow/clients/__init__.py
jetflow/clients/base.py
jetflow/clients/anthropic/__init__.py
jetflow/clients/anthropic/async_.py
jetflow/clients/anthropic/sync.py
jetflow/clients/anthropic/utils.py
jetflow/clients/gemini/__init__.py
jetflow/clients/gemini/async_.py
jetflow/clients/gemini/sync.py
jetflow/clients/gemini/utils.py
jetflow/clients/grok/__init__.py
jetflow-1.0.76.dist-info/licenses/LICENSE
jetflow-1.0.76.dist-info/METADATA
jetflow-1.0.76.dist-info/WHEEL
jetflow-1.0.76.dist-info/top_level.txt
jetflow-1.0.76.dist-info/RECORD
