Metadata-Version: 2.4
Name: jetflow
Version: 1.0.76
Summary: Lightweight, production-ready framework for building agentic workflows with LLMs
Author-email: Lucas Astorian <lucas@intellifin.ai>
License: MIT
Project-URL: Homepage, https://github.com/lucasastorian/jetflow
Project-URL: Repository, https://github.com/lucasastorian/jetflow
Project-URL: Issues, https://github.com/lucasastorian/jetflow/issues
Keywords: llm,agents,ai,langchain,openai,anthropic,gemini
Classifier: Development Status :: 5 - Production/Stable
Classifier: Intended Audience :: Developers
Classifier: License :: OSI Approved :: MIT License
Classifier: Programming Language :: Python :: 3
Classifier: Programming Language :: Python :: 3.10
Classifier: Programming Language :: Python :: 3.11
Classifier: Programming Language :: Python :: 3.12
Classifier: Topic :: Software Development :: Libraries :: Python Modules
Classifier: Topic :: Scientific/Engineering :: Artificial Intelligence
Requires-Python: >=3.10
License-File: LICENSE
Requires-Dist: pydantic>=2.0
Requires-Dist: httpx>=0.24.0
Requires-Dist: tiktoken>=0.5.0
Requires-Dist: lmdb>=1.4.0
Provides-Extra: openai
Requires-Dist: openai>=1.0.0; extra == "openai"
Requires-Dist: jiter>=0.5.0; extra == "openai"
Requires-Dist: tenacity>=8.0.0; extra == "openai"
Provides-Extra: anthropic
Requires-Dist: anthropic>=0.18.0; extra == "anthropic"
Requires-Dist: jiter>=0.5.0; extra == "anthropic"
Requires-Dist: tenacity>=8.0.0; extra == "anthropic"
Provides-Extra: grok
Requires-Dist: openai>=1.0.0; extra == "grok"
Requires-Dist: jiter>=0.5.0; extra == "grok"
Requires-Dist: tenacity>=8.0.0; extra == "grok"
Provides-Extra: groq
Requires-Dist: openai>=1.0.0; extra == "groq"
Requires-Dist: jiter>=0.5.0; extra == "groq"
Requires-Dist: tenacity>=8.0.0; extra == "groq"
Provides-Extra: gemini
Requires-Dist: google-genai>=1.50.0; extra == "gemini"
Provides-Extra: exec
Requires-Dist: numpy>=2.3.0; extra == "exec"
Requires-Dist: pandas>=2.3.0; extra == "exec"
Requires-Dist: matplotlib>=3.0.0; extra == "exec"
Requires-Dist: seaborn>=0.11.0; extra == "exec"
Provides-Extra: e2b
Requires-Dist: e2b>=1.0.0; extra == "e2b"
Requires-Dist: e2b-code-interpreter>=2.4.1; extra == "e2b"
Provides-Extra: exa
Requires-Dist: exa-py>=2.0.0; extra == "exa"
Provides-Extra: all
Requires-Dist: openai>=1.0.0; extra == "all"
Requires-Dist: anthropic>=0.18.0; extra == "all"
Requires-Dist: google-genai>=1.50.0; extra == "all"
Requires-Dist: jiter>=0.5.0; extra == "all"
Requires-Dist: tenacity>=8.0.0; extra == "all"
Requires-Dist: e2b>=1.0.0; extra == "all"
Requires-Dist: e2b-code-interpreter>=2.4.1; extra == "all"
Requires-Dist: exa-py>=2.0.0; extra == "all"
Provides-Extra: dev
Requires-Dist: pytest>=7.0.0; extra == "dev"
Requires-Dist: pytest-asyncio>=0.21.0; extra == "dev"
Requires-Dist: black>=23.0.0; extra == "dev"
Requires-Dist: mypy>=1.0.0; extra == "dev"
Requires-Dist: ruff>=0.1.0; extra == "dev"
Provides-Extra: docs
Requires-Dist: mkdocs>=1.5.0; extra == "docs"
Requires-Dist: mkdocs-material>=9.0.0; extra == "docs"
Requires-Dist: mkdocstrings[python]>=0.24.0; extra == "docs"
Dynamic: license-file
